{
  "project_info": {
    "project_number": "711104295228",
    "firebase_url": "https://cogentxapp.firebaseio.com",
    "project_id": "cogentxapp",
    "storage_bucket": "cogentxapp.appspot.com"
  },
  "client": [
    {
      "client_info": {
        "mobilesdk_app_id": "1:711104295228:android:684df47ff24c2a5a",
        "android_client_info": {
          "package_name": "com.app360ai.cogentx"
        }
      },
      "oauth_client": [
        {
          "client_id": "711104295228-mbttmkm7oc7i3rhokgr4ptu6vcvqmm7p.apps.googleusercontent.com",
          "client_type": 3
        }
      ],
      "api_key": [
        {
          "current_key": "AIzaSyD1xEafkNLMA5QniNo9uscLv19VlrirHlg"
        }
      ],
      "services": {
        "appinvite_service": {
          "other_platform_oauth_client": [
            {
              "client_id": "711104295228-mbttmkm7oc7i3rhokgr4ptu6vcvqmm7p.apps.googleusercontent.com",
              "client_type": 3
            },
            {
              "client_id": "711104295228-0a4k6v26mcpqv96rhvcddlk63hb54vbg.apps.googleusercontent.com",
              "client_type": 2,
              "ios_info": {
                "bundle_id": "app.360ai.cogentx"
              }
            }
          ]
        }
      }
    }
  ],
  "configuration_version": "1"
}